UNAGI/UNAGI_analyst.py
UNAGI/UNAGI_tool.py
UNAGI/__init__.py
UNAGI/data/brdID2cmapName.npy
UNAGI/data/cmap_drug_target_genes.npy
UNAGI/data/gesa_pathways.npy
UNAGI/data/human_encode.txt
UNAGI/data/mouse_predicted.txt
UNAGI/dynamic_graphs/__init__.py
UNAGI/dynamic_graphs/buildGraph.py
UNAGI/dynamic_graphs/distDistance.py
UNAGI/dynamic_regulatory_networks/__init__.py
UNAGI/dynamic_regulatory_networks/processIDREM.py
UNAGI/dynamic_regulatory_networks/processTFs.py
UNAGI/marker_discovery/__init__.py
UNAGI/marker_discovery/dynamic_markers.py
UNAGI/marker_discovery/dynamic_markers_helper.py
UNAGI/marker_discovery/hierachical_static_markers.py
UNAGI/model/__init__.py
UNAGI/model/distributions.py
UNAGI/model/models.py
UNAGI/perturbations/__init__.py
UNAGI/perturbations/analysis_perturbation.py
UNAGI/perturbations/compounds.py
UNAGI/perturbations/new_perturbation_strategy.py
UNAGI/perturbations/normalize_analysis_perturbation.py
UNAGI/perturbations/pathways.py
UNAGI/perturbations/perturbation.py
UNAGI/perturbations/perturbation_centroid.py
UNAGI/plotting/__init__.py
UNAGI/plotting/plot_cell_embeddings.py
UNAGI/plotting/plot_cell_type_composition.py
UNAGI/plotting/plot_hierarchical_markers_heatmap.py
UNAGI/plotting/plot_stage_dendrogram.py
UNAGI/train/__init__.py
UNAGI/train/customized_elbo.py
UNAGI/train/runner.py
UNAGI/train/trainer.py
UNAGI/utils/CPO_utils.py
UNAGI/utils/__init__.py
UNAGI/utils/analysis_helper.py
UNAGI/utils/attribute_utils.py
UNAGI/utils/evaluate.py
UNAGI/utils/gcn_utils.py
UNAGI/utils/h5adReader.py
UNAGI/utils/idrem_helper.py
UNAGI/utils/msigdb_data_overlapping.py
UNAGI/utils/trainer_utils.py
scunagi-0.5.10.dist-info/licenses/LICENSE.txt
scunagi-0.5.10.dist-info/METADATA
scunagi-0.5.10.dist-info/WHEEL
scunagi-0.5.10.dist-info/top_level.txt
scunagi-0.5.10.dist-info/RECORD
